LICENSE.txt
MANIFEST.in
PickleExploit.html
README.md
setup.py
PickleExploit/PickleExploit.py
PickleExploit/__init__.py
PickleExploit.egg-info/PKG-INFO
PickleExploit.egg-info/SOURCES.txt
PickleExploit.egg-info/dependency_links.txt
PickleExploit.egg-info/entry_points.txt
PickleExploit.egg-info/top_level.txt