Metadata-Version: 2.1
Name: PickleExploit
Version: 0.0.1
Summary: This package implement a Pickle Exploit Builder.
Home-page: https://github.com/mauricelambert/PickleExploit
Author: Maurice Lambert
Author-email: mauricelambert434@gmail.com
License: UNKNOWN
Platform: UNKNOWN
Classifier: Programming Language :: Python
Classifier: Development Status :: 5 - Production/Stable
Classifier: Natural Language :: English
Classifier: Operating System :: OS Independent
Classifier: Programming Language :: Python :: 3.8
Requires-Python: >=3.6
